canvas_chat/__init__.py
canvas_chat/__main__.py
canvas_chat/app.py
canvas_chat/config.py
canvas_chat/file_upload_handler_plugin.py
canvas_chat/file_upload_registry.py
canvas_chat/url_fetch_handler_plugin.py
canvas_chat/url_fetch_registry.py
canvas_chat/plugins/__init__.py
canvas_chat/plugins/code_handler.py
canvas_chat/plugins/ddg_endpoints.py
canvas_chat/plugins/git_repo_handler.py
canvas_chat/plugins/matrix_handler.py
canvas_chat/plugins/pdf_handler.py
canvas_chat/plugins/pdf_url_handler.py
canvas_chat/plugins/pptx_endpoints.py
canvas_chat/plugins/pptx_handler.py
canvas_chat/plugins/youtube_handler.py
canvas_chat/static/index.html
canvas_chat/static/css/base.css
canvas_chat/static/css/canvas.css
canvas_chat/static/css/components.css
canvas_chat/static/css/git-repo.css
canvas_chat/static/css/input.css
canvas_chat/static/css/matrix.css
canvas_chat/static/css/modals.css
canvas_chat/static/css/nodes.css
canvas_chat/static/css/style.css
canvas_chat/static/css/toolbar.css
canvas_chat/static/js/app.js
canvas_chat/static/js/canvas.js
canvas_chat/static/js/chat.js
canvas_chat/static/js/crdt-graph.js
canvas_chat/static/js/event-emitter.js
canvas_chat/static/js/feature-plugin.js
canvas_chat/static/js/feature-registry.js
canvas_chat/static/js/file-upload-handler-plugin.js
canvas_chat/static/js/file-upload-handler.js
canvas_chat/static/js/file-upload-registry.js
canvas_chat/static/js/graph-types.js
canvas_chat/static/js/highlight-utils.js
canvas_chat/static/js/layout.js
canvas_chat/static/js/modal-manager.js
canvas_chat/static/js/model-utils.ts
canvas_chat/static/js/node-protocols.js
canvas_chat/static/js/node-registry.js
canvas_chat/static/js/plugin-events.js
canvas_chat/static/js/plugin-test-harness.js
canvas_chat/static/js/pyodide-runner.js
canvas_chat/static/js/scroll-utils.js
canvas_chat/static/js/search.js
canvas_chat/static/js/slash-command-menu.js
canvas_chat/static/js/sse.js
canvas_chat/static/js/storage.js
canvas_chat/static/js/streaming-manager.js
canvas_chat-0.1.91.dist-info/METADATA
canvas_chat-0.1.91.dist-info/WHEEL
canvas_chat-0.1.91.dist-info/entry_points.txt
canvas_chat-0.1.91.dist-info/RECORD
