Metadata-Version: 2.4
Name: canvas-chat
Version: 0.1.91
Summary: A visual, non-linear chat interface where conversations are nodes on an infinite canvas
Requires-Python: >=3.11
Requires-Dist: beautifulsoup4<5,>=4.14.3
Requires-Dist: build<2,>=1.3.0
Requires-Dist: ddgs<10,>=9.0.0
Requires-Dist: defusedxml
Requires-Dist: exa-py<3,>=2.0.2
Requires-Dist: fastapi>=0.115.0
Requires-Dist: html2text<2026,>=2025.4.15
Requires-Dist: httpx<0.29,>=0.28.1
Requires-Dist: litellm>=1.50.0
Requires-Dist: llamabot>=0.17.0
Requires-Dist: modal<2,>=1.3.0.post1
Requires-Dist: pillow<13,>=12.1.0
Requires-Dist: pydantic>=2.0.0
Requires-Dist: pymupdf>=1.24.0
Requires-Dist: pytest<10,>=9.0.2
Requires-Dist: python-multipart>=0.0.9
Requires-Dist: python-pptx>=1.0.0
Requires-Dist: python-slugify
Requires-Dist: ruamel-yaml<0.20,>=0.19.1
Requires-Dist: sse-starlette>=2.0.0
Requires-Dist: typer
Requires-Dist: uvicorn>=0.32.0
Requires-Dist: youtube-transcript-api<2,>=1.2.3
Provides-Extra: dev
Requires-Dist: httpx>=0.27.0; extra == 'dev'
Requires-Dist: pytest>=8.0.0; extra == 'dev'
